{"cameraMode":{"drawMode":0,"name":"Shaded","section":"Shading Mode"},"sceneLighting":true,"audioPlay":false,"sceneViewState":{"showFog":true,"showMaterialUpdate":false,"showSkybox":true,"showFlares":true,"showImageEffects":true,"showParticleSystems":true},"in2DMode":false,"pivot":{"x":11.809094429016114,"y":2.9368209838867189,"z":10.248233795166016},"rotation":{"x":0.1513388752937317,"y":-0.2960245609283447,"z":0.04756364971399307,"w":0.9419175386428833},"size":1.2494051456451417,"orthographic":false}